ccdfits/__init__.py
ccdfits/_auxiliary.py
ccdfits/classes.py
ccdfits/extract.py
ccdfits/gfits.py
ccdfits/processing.py
ccdfits/utilities.py
ccdfits-1.0.0.dist-info/LICENSE
ccdfits-1.0.0.dist-info/METADATA
ccdfits-1.0.0.dist-info/WHEEL
ccdfits-1.0.0.dist-info/top_level.txt
ccdfits-1.0.0.dist-info/RECORD
