Metadata-Version: 2.1
Name: ccdfits
Version: 1.0.0
Summary: Utilities to work with .fits files that were taken with CCDs and Skipper CCDs
Home-page: https://gitlab.com/nicolaseavalos/ccdfits
Author: Nicolás Avalos
Author-email: nicolaseavalos@gmail.com
Classifier: Programming Language :: Python :: 3
Classifier: License :: OSI Approved :: MIT License
Classifier: Operating System :: OS Independent
Requires-Python: >=3.6
License-File: LICENSE
Requires-Dist: numpy
Requires-Dist: scipy
Requires-Dist: matplotlib
Requires-Dist: astropy
